Metadata-Version: 2.1
Name: django-dynamic-fixture-dj31
Version: 3.1.1
Summary: A temporary fork of django-dynamic-fixture that is compatible with Django 3.1.
Home-page: https://github.com/paulocheque/django-dynamic-fixture
Author: paulocheque
Author-email: paulocheque@gmail.com
License: MIT
Keywords: python django testing fixture
Platform: UNKNOWN
Classifier: Framework :: Django
Classifier: Operating System :: OS Independent
Classifier: Topic :: Software Development
Classifier: Programming Language :: Python :: 2.7
Classifier: Programming Language :: Python :: 3.5
Classifier: Programming Language :: Python :: 3.6
Classifier: Programming Language :: Python :: 3.7
Classifier: Programming Language :: Python :: 3.8
Classifier: Programming Language :: Python :: Implementation :: PyPy
Provides-Extra: test
